{
  "@context": "https://schema.org",
  "@type": "BlogPosting",
  "headline": "Affordable Server Recycling in Kalamassery: Complete Pricing",
  "description": "Looking for reliable server recycling in Kalamassery? This comprehensive guide covers everything you need to know about e-waste management in Kalamassery, inclu...",
  "image": "https://www.ewastekochi.com/images/blog/affordable-server-recycling-in-kalamassery-complete-pricing-kalamassery.jpg",
  "author": {
    "@type": "Organization",
    "name": "EWaste Kochi",
    "url": "https://www.ewastekochi.com"
  },
  "publisher": {
    "@type": "Organization",
    "name": "EWaste Kochi",
    "logo": {
      "@type": "ImageObject",
      "url": "https://www.ewastekochi.com/logo.png"
    }
  },
  "datePublished": "2025-05-21",
  "dateModified": "2025-05-21",
  "mainEntityOfPage": {
    "@type": "WebPage",
    "@id": "https://www.ewastekochi.com/blog/affordable-server-recycling-in-kalamassery-complete-pricing-kalamassery/"
  },
  "articleSection": "corporate",
  "keywords": "Server Recycling, Kalamassery, server disposal, data center recycling, rack disposal",
  "wordCount": 1407,
  "speakable": {
    "@type": "SpeakableSpecification",
    "cssSelector": [
      "h1",
      "h2",
      ".blog-intro"
    ]
  },
  "about": {
    "@type": "Thing",
    "name": "Server Recycling"
  },
  "locationCreated": {
    "@type": "Place",
    "name": "Kalamassery",
    "address": {
      "@type": "PostalAddress",
      "addressLocality": "Kalamassery",
      "addressRegion": "Kerala",
      "postalCode": "683104",
      "addressCountry": "IN"
    }
  }
}