{
  "@context": "https://schema.org",
  "@type": "BlogPosting",
  "headline": "Server Recycling vs Server Disposal in Kalamassery",
  "description": "Kalamassery residents and businesses often wonder about proper disposal. Our detailed guide explains server recycling services available in Kalamassery, with ex...",
  "image": "https://www.ewastekochi.com/images/blog/server-recycling-vs-server-disposal-in-kalamassery-kalamassery-1.jpg",
  "author": {
    "@type": "Organization",
    "name": "EWaste Kochi",
    "url": "https://www.ewastekochi.com"
  },
  "publisher": {
    "@type": "Organization",
    "name": "EWaste Kochi",
    "logo": {
      "@type": "ImageObject",
      "url": "https://www.ewastekochi.com/logo.png"
    }
  },
  "datePublished": "2025-05-21",
  "dateModified": "2025-05-21",
  "mainEntityOfPage": {
    "@type": "WebPage",
    "@id": "https://www.ewastekochi.com/blog/server-recycling-vs-server-disposal-in-kalamassery-kalamassery-1/"
  },
  "articleSection": "corporate",
  "keywords": "Server Recycling, Kalamassery, server disposal, data center recycling, rack disposal",
  "wordCount": 1458,
  "speakable": {
    "@type": "SpeakableSpecification",
    "cssSelector": [
      "h1",
      "h2",
      ".blog-intro"
    ]
  },
  "about": {
    "@type": "Thing",
    "name": "Server Recycling"
  },
  "locationCreated": {
    "@type": "Place",
    "name": "Kalamassery",
    "address": {
      "@type": "PostalAddress",
      "addressLocality": "Kalamassery",
      "addressRegion": "Kerala",
      "postalCode": "683104",
      "addressCountry": "IN"
    }
  }
}